Workbook

Sheet ESTRUCTURA
A1: OBSERVATORIO INMOBILIARIO NACIONÁL
A2: MODELO PARA LA PRESENTACION DE DATOS ANTE EL OBSERVATORIO INMOBILIARIO NACIONAL
A3: Código | B3: Componente | C3: Capa Geografica | D3: Tabla
B4: DINAMICA INMOBILIARIA | C4: =+'CAPA GEOGRÁFICA'!$C$6 -> Predios | D4: =+TABLA!$C$6 -> Predios
D5: Fisico/Construcciones
D6: Fisico/Terrenos
D7: Juridico/Tradicion
D8: Ofertas
D9: Avaluos

Sheet CAPA GEOGRÁFICA
B2: ESTRUCTURA DE DATOS - CAPAS GEOGRÁFICAS
B4: Descripción Tema | C4: Predios
C5: Comprende los predios de interes que se encuetren dentro de las zonas de estudio del gestor catastral
B6: Feature Class: | C6: Predios
B7: Geometría: | C7: Poligono
B8: CAMPO | C8: TIPO DE DATO | D8: DESCRIPCIÓN | E8: DOMINIO | F8: OBLIGACIÓN/CONDICIÓN | G8: PAQUETE LADM-COL | H8: CLASE
B9: ID_PREDIO | C9: String | D9: Identificador unico del predio a cargo del observatorio | E9: N/A | F9: Obligatorio
B10: CODIGO_OBSERVATORIO | C10: String | D10: Codigo del Observatorio directamente proporcionado una vez que el usuario se haya registrado en la pagina oficial del observatorio Inmobiliario Nacional | E10: N/A | F10: Obligatorio
B11: DEPARTAMENTO | C11: String | D11: Departamento de Colombia donde se encuentra ubicado el Predio | E11: N/A | F11: Obligatorio | G11: Unidad Administrativa Basica | H11: Clase. LC_Predio
B12: MUNICIPIO | C12: String | D12: Municipio de Colombia donde se encuentra ubicado el Predio | E12: N/A | F12: Obligatorio | G12: Unidad Administrativa Basica | H12: Clase. LC_Predio
B13: NUPRE | C13: String | D13: Es un código único para identificar los inmuebles tanto en los sistemas de información catastral como registral. El NUPRE no implicará supresión de la numeración catastral ni registral asociada a la cédula catastral ni a la matrícula inmobiliaria actual. | E13: N/A | F13: Obligatorio | G13: Unidad Administrativa Basica | H13: Clase. LC_Predio
B14: NUMERO_PREDIAL_ANTIGUO | C14: String | D14: Anterior Código numérico de veinte (20) dígitos | E14: N/A | F14: Obligatorio | G14: Unidad Administrativa Basica | H14: Clase. LC_Predio
B15: NUMERO PREDIAL NUEVO | C15: String | D15: Nuevo Código numérico de treinta (30) dígitos | E15: N/A | F15: Obligatorio | G15: Unidad Administrativa Basica | H15: Clase. LC_Predio
B16: CODIGO_ORIP | C16: String | D16: Codigo circulo registral | E16: N/A | F16: Obligatorio | G16: Unidad Administrativa Basica | H16: Clase. LC_Predio
B17: MATRICULA_INMOBILIARIA | C17: String | D17: Numero de Matricula inmobiliaria | E17: N/A | F17: Obligatorio | G17: Unidad Administrativa Basica | H17: Clase. LC_Predio
B18: GESTOR_CATASTRAL | C18: String | D18: Nombre o codigo del gestor catastral que proporciona la información | E18: N/A | F18: Obligatorio
B19: OPERADOR_CATASTRAL | C19: String | D19: Nombre del operador catastral | E19: N/A | F19: Opcional
B20: ZONA | C20: Dominio | D20: Especificar si el predio es urbano o rural | E20: =+DOMINIOS!C2 -> Dom_ClaseSueloTipo | F20: Obligatorio
B21: NOMBRE_SECTOR | C21: String | D21: Código de identificación única del sector catastral. | E21: N/A | F21: Opcional | G21: Submodelo de Cartografia ctastral | H21: Clase. CC_Sector_Urbano
B22: NOMBRE_LOCALIDAD_COMUNA | C22: String | D22: Nombre de la localidad o comuna aprobada por el acuerdo municipal. | E22: N/A | F22: Opcional | G22: Submodelo de Cartografia ctastral | H22: Clase. CC_Localidad_Comun a
B23: NOMBRE_BARRIO | C23: String | D23: Nombre del barrio aprobado en el acuerdo municipal. | E23: N/A | F23: Obligatorio | G23: Submodelo de Cartografia ctastral | H23: Clase. CC_Barrio
B24: VEREDA_MANZANA | C24: String | D24: Nombre de la verada o numero de la manzana de ubicación del predio | E24: N/A | F24: Obligatorio | G24: Unidad Espacial | H24: Clase. LC_Terreno
B25: TIPO | C25: Dominio | D25: Indica el tipo predio para efectos catastrales. | E25: =+DOMINIOS!C24 -> Dom_Predio_Tipo | F25: Obligatorio | G25: Unidad Administrativa Basica | H25: Clase. LC_Predio
B26: CONDICION_PREDIO | C26: Dominio | D26: Especifiar que tipo de condicion tiene la propiedad dentro de los dominos | E26: =+DOMINIOS!C35 -> Dom_Condicion_Predio_Tipo | F26: Obligatorio | G26: Unidad Administrativa Basica | H26: Clase. LC_Predio
B27: COPROPIEDAD | C27: String | D27: Identificador del predio matriz bajo el régimen de propiedad horizontal. | E27: N/A | F27: Condicional | G27: Unidad Administrativa Basica | H27: LC_Predio_Copropiedad
B28: PREDIO | C28: String | D28: Identificador de la unidad predial | E28: N/A | F28: Condicional | G28: Unidad Administrativa Basica | H28: LC_Predio_Copropiedad
B29: COEFICIENTE | C29: Number | D29: Coeficiente de copropiedad de la unidad predial. | E29: N/A | F29: Condicional | G29: Unidad Administrativa Basica | H29: LC_Predio_Copropiedad
B30: NUMERO_EDIFICIO_O_TORRE | C30: Number | D30: Torreo o edificio donde se encuentra el inmueble en PH | E30: N/A | F30: Condicional
B31: NUMERO_PISO_EDIFICIO | C31: Number | D31: Numero de piso dentro de la torre o edificio donde esta ubicado el apartamento en ph | E31: N/A | F31: Condicional
B32: NUMERO_UNIDAD | C32: Number | D32: Numero de la unidad dentro de la torreo o edificio | E32: N/A | F32: Condicional
B33: NUMERO_TORRES | C33: Number | D33: Número total de torres en el PH o Condominio | E33: N/A | F33: Condicional | G33: Unidad Administrativa Basica | H33: LC_DatosPHCondominio
B34: TOTAL_PISOS_TORRES | C34: Number | D34: Total de pisos por torre en el PH o Condominio. | E34: N/A | F34: Condicional | G34: Insumos del Gestor Catastral | H34: Clase. GC_DatosTorrePH
B35: TOTAL_UNIDADES_PRIVADAS | C35: Number | D35: Total de unidades privadas en el PH o Condominio. | E35: N/A | F35: Condicional | G35: Unidad Administrativa Basica | H35: LC_DatosPHCondominio
B36: TOTAL_SOTANOS | C36: Number | D36: Total de sótanos en PH o Condominio | E36: N/A | F36: Condicional | G36: Insumos del Gestor Catastral | H36: Clase. GC_Datos_PH_Condo minio
B37: TOTAL_PARQUEADEROS | C37: Number | D37: Total de parqueaderos en PH o Condominio | E37: N/A | F37: Condicional
B38: AVALUO_CATASTRAL | C38: Number | D38: Valor catastral del predio, obtenido mediante investigación y análisis estadístico del mercado inmobiliario y la metodología de aplicación correspondiente | E38: N/A | F38: Opcional | G38: Unidad Administrativa Basica | H38: Clase. LC_Predio
B39: DESTINACION_ECONOMICA | C39: Dominio | D39: Es la clasificación para fines estadísticos que se da a cada inmueble en su conjunto–terreno, construcciones o edificaciones-, en el momento de la identificación predial de conformidad con la actividad predominante que en él se desarrolle. | E39: =+DOMINIOS!C75 -> Dom_Destinacion_Economica | F39: Obligatorio | G39: Unidad Administrativa Basica | H39: Clase. LC_DatosAdicionalesLevantamientoCatastral
B40: DIRECCION | C40: Dominio | D40: Dirección del predio. | E40: =+DOMINIOS!$C$107 -> Ext_Direccion | F40: Obligatorio | G40: Unidad Administrativa Basica | H40: Clase. LC_Predio

Sheet TABLA
B2: ESTRUCTURA DE DATOS -TABLAS
B4: Descripción Tema | C4: Predios
C5: Comprende los predios de interes que se encuetren dentro de las zonas de estudio del gestor catastral
B6: Tabla | C6: Predios
B7: CAMPO | C7: TIPO DE DATO | D7: DESCRIPCIÓN | E7: DOMINIO | F7: OBLIGACIÓN/CONDICIÓN | G7: PAQUETE LADM-COL | H7: CLASE
B8: ID_PREDIO | C8: String | D8: Identificador unico del predio a cargo del observatorio | E8: N/A | F8: Obligatorio
B9: CODIGO_OBSERVATORIO | C9: String | D9: Codigo del Observatorio directamente proporcionado una vez que el usuario se haya registrado en la pagina oficial del observatorio Inmobiliario Nacional | E9: N/A | F9: Obligatorio
B10: DEPARTAMENTO | C10: String | D10: Departamento de Colombia donde se encuentra ubicado el Predio | E10: N/A | F10: Obligatorio | G10: Unidad Administrativa Basica | H10: Clase. LC_Predio
B11: MUNICIPIO | C11: String | D11: Municipio de Colombia donde se encuentra ubicado el Predio | E11: N/A | F11: Obligatorio | G11: Unidad Administrativa Basica | H11: Clase. LC_Predio
B12: NUPRE | C12: String | D12: Es un código único para identificar los inmuebles tanto en los sistemas de información catastral como registral. El NUPRE no implicará supresión de la numeración catastral ni registral asociada a la cédula catastral ni a la matrícula inmobiliaria actual. | E12: N/A | F12: Obligatorio | G12: Unidad Administrativa Basica | H12: Clase. LC_Predio
B13: NUMERO_PREDIAL_ANTIGUO | C13: String | D13: Anterior Código numérico de veinte (20) dígitos | E13: N/A | F13: Obligatorio | G13: Unidad Administrativa Basica | H13: Clase. LC_Predio
B14: NUMERO PREDIAL NUEVO | C14: String | D14: Nuevo Código numérico de treinta (30) dígitos | E14: N/A | F14: Obligatorio | G14: Unidad Administrativa Basica | H14: Clase. LC_Predio
B15: CODIGO_ORIP | C15: String | D15: Codigo circulo registral | E15: N/A | F15: Obligatorio | G15: Unidad Administrativa Basica | H15: Clase. LC_Predio
B16: MATRICULA_INMOBILIARIA | C16: String | D16: Numero de Matricula inmobiliaria | E16: N/A | F16: Obligatorio | G16: Unidad Administrativa Basica | H16: Clase. LC_Predio
B17: GESTOR_CATASTRAL | C17: String | D17: Nombre o codigo del gestor catastral que proporciona la información | E17: N/A | F17: Obligatorio
B18: OPERADOR_CATASTRAL | C18: String | D18: Nombre del operador catastral | E18: N/A | F18: Opcional
B19: ZONA | C19: Dominio | D19: Especificar si el predio es urbano o rural | E19: =+DOMINIOS!C2 -> Dom_ClaseSueloTipo | F19: Obligatorio
B20: NOMBRE_SECTOR | C20: String | D20: Código de identificación única del sector catastral. | E20: N/A | F20: Opcional | G20: Submodelo de Cartografia ctastral | H20: Clase. CC_Sector_Urbano
B21: NOMBRE_LOCALIDAD_COMUNA | C21: String | D21: Nombre de la localidad o comuna aprobada por el acuerdo municipal. | E21: N/A | F21: Opcional | G21: Submodelo de Cartografia ctastral | H21: Clase. CC_Localidad_Comun a
B22: NOMBRE_BARRIO | C22: String | D22: Nombre del barrio aprobado en el acuerdo municipal. | E22: N/A | F22: Obligatorio | G22: Submodelo de Cartografia ctastral | H22: Clase. CC_Barrio
B23: VEREDA_MANZANA | C23: String | D23: Nombre de la verada o numero de la manzana de ubicación del predio | E23: N/A | F23: Obligatorio | G23: Unidad Espacial | H23: Clase. LC_Terreno
B24: TIPO | C24: Dominio | D24: Indica el tipo predio para efectos catastrales. | E24: =+DOMINIOS!C24 -> Dom_Predio_Tipo | F24: Obligatorio | G24: Unidad Administrativa Basica | H24: Clase. LC_Predio
B25: CONDICION_PREDIO | C25: Dominio | D25: Especifiar que tipo de condicion tiene la propiedad dentro de los dominos | E25: =+DOMINIOS!C35 -> Dom_Condicion_Predio_Tipo | F25: Obligatorio | G25: Unidad Administrativa Basica | H25: Clase. LC_Predio
B26: COPROPIEDAD | C26: String | D26: Identificador del predio matriz bajo el régimen de propiedad horizontal. | E26: N/A | F26: Condicional | G26: Unidad Administrativa Basica | H26: LC_Predio_Copropiedad
B27: PREDIO | C27: String | D27: Identificador de la unidad predia | E27: N/A | F27: Condicional | G27: Unidad Administrativa Basica | H27: LC_Predio_Copropiedad
B28: COEFICIENTE | C28: Number | D28: Coeficiente de copropiedad de la unidad predial. | E28: N/A | F28: Condicional | G28: Unidad Administrativa Basica | H28: LC_Predio_Copropiedad
B29: NUMERO_EDIFICIO_O_TORRE | C29: Number | D29: Torreo o edificio donde se encuentra el inmueble en PH | E29: N/A | F29: Condicional
B30: NUMERO_PISO_EDIFICIO | C30: Number | D30: Numero de piso dentro de la torre o edificio | E30: N/A | F30: Condicional
B31: NUMERO_UNIDAD | C31: Number | D31: Numero de la unidad dentro de la torreo o edificio | E31: N/A | F31: Condicional
B32: NUMERO_TORRES | C32: Number | D32: Número de torres en el PH o Condominio | E32: N/A | F32: Condicional | G32: Unidad Administrativa Basica | H32: LC_DatosPHCondominio
B33: TOTAL_PISOS_TORRES | C33: Number | D33: Total de pisos por torre en el PH o Condominio. | E33: N/A | F33: Condicional | G33: Insumos del Gestor Catastral | H33: Clase. GC_DatosTorrePH
B34: TOTAL_UNIDADES_PRIVADAS | C34: Number | D34: Total de unidades privadas en el PH o Condominio. | E34: N/A | F34: Condicional | G34: Unidad Administrativa Basica | H34: LC_DatosPHCondominio
B35: TOTAL_SOTANOS | C35: Number | D35: Total de sótanos en PH o Condominio | E35: N/A | F35: Condicional | G35: Insumos del Gestor Catastral | H35: Clase. GC_Datos_PH_Condo minio
B36: TOTAL_PARQUEADEROS | C36: Number | D36: Total de parqueaderos en PH o Condominio | E36: N/A | F36: Condicional
B37: AVALUO_CATASTRAL | C37: Number | D37: Valor catastral del predio, obtenido mediante investigación y análisis estadístico del mercado inmobiliario y la metodología de aplicación correspondiente | E37: N/A | F37: Opcional | G37: Unidad Administrativa Basica | H37: Clase. LC_Predio
B38: DESTINACION_ECONOMICA | C38: Dominio | D38: Es la clasificación para fines estadísticos que se da a cada inmueble en su conjunto–terreno, construcciones o edificaciones-, en el momento de la identificación predial de conformidad con la actividad predominante que en él se desarrolle. | E38: =+DOMINIOS!C75 -> Dom_Destinacion_Economica | F38: Obligatorio | G38: Unidad Administrativa Basica | H38: Clase. LC_DatosAdicionalesLevantamientoCatastral
B39: DIRECCION | C39: Dominio | D39: Dirección del predio. | E39: =+DOMINIOS!$C$107 -> Ext_Direccion | F39: Obligatorio | G39: Unidad Administrativa Basica | H39: Clase. LC_Predio
B42: Descripción Tema | C42: Fisico/Construcciones
C43: Comprende la informacion de las construcciones que estan relacionadas con la calse predios que se encuetren dentro de las zonas de estudio del gestor catastral
B44: Tabla | C44: Fisico/Construcciones
B45: CAMPO | C45: TIPO DE DATO | D45: DESCRIPCIÓN | E45: DOMINIO | F45: OBLIGACIÓN/CONDICIÓN | G45: PAQUETE LADM-COL | H45: CLASE
B46: ID_CONSTRUCCION | C46: String | D46: Identificador unico de la construccion que se encuentra ubicada dentro de los limites del predio. | E46: N/A | F46: Obligatorio
B47: ID_PREDIO | C47: String | D47: Identificador unico del predio a cargo del observatorio | E47: N/A | F47: Obligatorio
B48: CODIGO_OBSERVATORIO | C48: String | D48: Codigo del Observatorio directamente proporcionado una vez que el usuario se haya registrado en la pagina oficial del observatorio Inmobiliario Nacional | E48: N/A | F48: Obligatorio
B49: NUMERO_PREDIAL_ANTIGUO | C49: String | D49: Numero predial actual | E49: N/A | F49: Obligatorio | G49: Unidad Administrativa Basica | H49: Clase. LC_Predio
B50: NUMERO PREDIAL NUEVO | C50: String | D50: Numero predial Anterior | E50: N/A | F50: Obligatorio | G50: Unidad Administrativa Basica | H50: Clase. LC_Predio
B51: MATRICULA_INMOBILIARIA | C51: String | D51: Numero de Matricula inmobiliaria | E51: N/A | F51: Obligatorio | G51: Unidad Administrativa Basica | H51: Clase. LC_Predio
B52: IDENTIFICADOR | C52: String | D52: Identificador de la unidad de construcción, su codificación puede ser por letras del abecedario. | E52: N/A | F52: Obligatorio | G52: Unidad Espacial | H52: Clase. LC_Construcción
B53: TIPO_DE_CONSTRUCCION | C53: Dominio | D53: Indica si la construcción es de tipo convencional o no convencional | E53: =+DOMINIOS!C92 -> Dom_ConstruccionesTipo | F53: Obligatorio | G53: Unidad Espacial | H53: Clase. LC_Construcción
B54: TIPO_UNIDAD_CONSTRUCCION | C54: Dominio | D54: Indica si la unidad de construcción es residencial, comercial, industrial o anexo | E54: =+DOMINIOS!$C$98 -> Dom_UnidadConstruccionTipo | F54: Obligatorio | G54: Unidad Espacial | H54: Clase. LC_UnidadConstruccion
B55: TIPO_PLANTA | C55: Dominio | D55: Indica el tipo de planta donde se ubica la unidad de construcción | E55: =+DOMINIOS!$C$122 -> Dom_ConstruccionPlantaTipo | F55: Obligatorio | G55: Unidad Espacial | H55: Clase. LC_UnidadConstruccion
B56: PLANTA_UBICACION | C56: Number | D56: Indica numéricamente la ubicación del predio de acuerdo al tipo de planta. | E56: N/A | F56: Obligatorio | G56: Unidad Espacial | H56: LC_UnidadConstrucci on
B57: NUMERO_PISOS | C57: Number | D57: Número total de pisos de la construcción. | E57: N/A | F57: Obligatorio | G57: Unidad Espacial | H57: Clase. LC_Construcción
B58: NUMERO_SOTANOS | C58: Number | D58: Número total de sótanos de la construcción. | E58: N/A | F58: Obligatorio | G58: Unidad Espacial | H58: Clase. LC_Construcción
B59: NUMERO_SEMISONTANOS | C59: Number | D59: Número total de semisótanos de la construcción. | E59: N/A | F59: Obligatorio | G59: Unidad Espacial | H59: Clase. LC_Construcción
B60: ANIO_CONSTRUCCION | C60: Number | D60: Año de edificación de la construcción. | E60: N/A | F60: Obligatorio | G60: Unidad Espacial | H60: Clase. LC_Construcción
B61: AVALUO_CONSTRUCCION | C61: Number | D61: Avalúo total catastral de la construcción | E61: N/A | F61: Obligatorio | G61: Unidad Espacial | H61: Clase. LC_Construcción
B62: AREA_CONSTRUCCION | C62: Number | D62: Área total construida. | E62: N/A | F62: Obligatorio | G62: Unidad Espacial | H62: Clase. LC_Construcción
B63: ALTURA | C63: Number | D63: Altura total de la construcción. | E63: N/A | F63: Opcional | G63: Unidad Espacial | H63: Clase. LC_Construcción
B64: NUMERO_HABITACIONES | C64: Number | D64: Número total de habitaciones en la unidad de construcción. | E64: N/A | F64: Obligatorio | G64: Unidad Espacial | H64: Clase. LC_UnidadConstruccion
B65: NUMERO_BANNOS | C65: Number | D65: Número total de baños en la unidad de construcción. | E65: N/A | F65: Obligatorio | G65: Unidad Espacial | H65: Clase. LC_UnidadConstruccion
B66: NUMERO_LOCALES | C66: Number | D66: Número total de locales en la unidad de construcción. | E66: N/A | F66: Obligatorio | G66: Unidad Espacial | H66: Clase. LC_UnidadConstruccion
B67: TOTAL_PISOS | C67: Number | D67: Número total de pisos en la unidad de construcción. | E67: N/A | F67: Obligatorio | G67: Unidad Espacial | H67: Clase. LC_UnidadConstruccion
B68: USO | C68: Dominio | D68: Actividad que se desarrolla en una unidad de construcción. | E68: =+DOMINIOS!$C$131 -> Dom_UsoUConsTipo | F68: Obligatorio | G68: Unidad Espacial | H68: Clase. LC_UnidadConstruccion
B69: PUNTUACION | C69: Number | D69: Puntaje de las edificaciones de acuerdo a sus características constructivas. | E69: N/A | F69: Obligatorio | G69: Submodelo de Avaluos | H69: Clase. AV_Tabla_Calificació n_Construccion
B70: TIPO_TIPOLOGIA | C70: Dominio | D70: Son las características de diseño y constructivas especiales de las construcciones y/o edificaciones | E70: =+DOMINIOS!$C$237 -> Dom_TipologiaTipo | F70: Obligatorio | G70: Unidad Espacial | H70: Clase. LC_Tipologia_Constr ucción
B71: VALOR_M2_CONSTRUCCION | C71: Number | D71: Valor por metros cuadrado de construcción clasificando por uso y puntaje de las unidades de construcción. | E71: N/A | F71: Obligatorio | G71: Submodelo de Avaluos | H71: Clase. AV_Tabla_Calificació n_Construccion
B72: AREA_PRIVADA_CONSTRUIDA | C72: Number | D72: Área total privada de la unidad de construcción para los predios en régimen de propiedad horizontal. | E72: N/A | F72: Condicional | G72: Unidad Espacial | H72: Clase. LC_UnidadConstruccion
B73: CLASE_CALIFICACION | C73: Dominio | D73: Indica los elementos generales de la calificación de la construcción de acuerdo al método vigente. | E73: =+DOMINIOS!$C$266 -> Dom_ClaseCalificacionTipo | F73: Opcional | G73: Unidad Espacial | H73: Clase. LC_Grupo Calificación
B74: CONSERVACION | C74: Dominio | D74: Estado de conservación del grupo calificado. | E74: =+DOMINIOS!$C$275 -> Dom_EstadoConservacionTipo | F74: Obligatorio | G74: Unidad Espacial | H74: Clase. LC_Grupo Calificación
B77: Descripción Tema | C77: Fisico/Terrenos
C78: Comprende la informacion de los terrenos que estan relacionados con la clase predios que se encuetren dentro de las zonas de estudio del gestor catastral
B79: Tabla | C79: Fisico/Terrenos
B80: CAMPO | C80: TIPO DE DATO | D80: DESCRIPCIÓN | E80: DOMINIO | F80: OBLIGACIÓN/CONDICIÓN | G80: PAQUETE LADM-COL | H80: CLASE
B81: ID_TERRENO | C81: String | D81: Identificador unico del terreno vinculado al predio | E81: N/A | F81: Obligatorio
B82: ID_PREDIO | C82: String | D82: Identificador unico del predio a cargo del observatorio | E82: N/A | F82: Obligatorio
B83: CODIGO_OBSERVATORIO | C83: String | D83: Codigo del Observatorio directamente proporcionado una vez que el usuario se haya registrado en la pagina oficial del observatorio Inmobiliario Nacional | E83: N/A | F83: Obligatorio
B84: NUMERO_PREDIAL_ANTIGUO | C84: String | D84: Numero predial actual | E84: N/A | F84: Obligatorio | G84: Unidad Administrativa Basica | H84: Clase. LC_Predio
B85: NUMERO PREDIAL NUEVO | C85: String | D85: Numero predial Anterior | E85: N/A | F85: Obligatorio | G85: Unidad Administrativa Basica | H85: Clase. LC_Predio
B86: MATRICULA_INMOBILIARIA | C86: Double | D86: Numero de Matricula inmobiliaria | E86: N/A | F86: Obligatorio | G86: Unidad Administrativa Basica | H86: Clase. LC_Predio
B87: CLASE_DE_SUELO | C87: Dominio | D87: Clasificación del suelo según el instrumento de planeación vigente | E87: =+DOMINIOS!$C$2 -> Dom_ClaseSueloTipo | F87: Obligatorio | G87: Unidad Administrativa Basica | H87: Clase. LC_DatosAdicionales LevantamientoCatast ral
B88: CATEGORIA_SUELO | C88: Dominio | D88: Categoría del suelo según el instrumento de planeación vigente. | E88: =+DOMINIOS!$C$9 -> Dom_CategoriaSueloTipo | F88: Opcional | G88: Unidad Administrativa Basica | H88: Clase. LC_DatosAdicionales LevantamientoCatast ral
B89: AREA_TOTAL_TERRENO | C89: Number | D89: Área total del terreno que corresponde al valor asignado en el proceso de valoración economica masiva al terreno del predio, si es PH o Condominio Area total del predio Matriz. | E89: N/A | F89: Obligatorio | G89: Unidad Administrativa Basica | H89: Clase. LC_DatosPHCondomi nio
B90: AREA_CALCULADA | C90: Number | D90: Área de predio resultado de los calculos realizados en el proceso de levantamiento planimetrico | E90: N/A | F90: Opcional | G90: Unidad Espacial | H90: Clase. LC_Terreno
B91: AREA_REGISTRAL | C91: Number | D91: Área del predio que se encuentra inscrita en el Folio de Matricula Inmobiliaria | E91: N/A | F91: Opcional | G91: Unidad Administrativa Basica | H91: Clase. LC_DatosAdicionales LevantamientoCatast ral
B92: PARTICIAPACION_EN_EL_TERRENO | C92: Number | D92: Area total de participacion del terreno/ Aplica solo en PH o condominios | E92: N/A | F92: Condicional
B93: AVALÚO_DE_TERRENO | C93: Number | D93: Avaluo total del terreno | E93: N/A | F93: Obligatorio | G93: Unidad Espacial | H93: Clase. LC_Terreno
B96: Descripción Tema | C96: Juridico/Tradición
C97: Comprende la informacion juridica sobre predios que se encuetren dentro de las zonas de estudio del gestor catastral
B98: Tabla | C98: Juridico/Tradición
B99: CAMPO | C99: TIPO DE DATO | D99: DESCRIPCIÓN | E99: DOMINIO | F99: OBLIGACIÓN/CONDICIÓN | G99: PAQUETE LADM-COL | H99: CLASE
B100: ID_PREDIO | C100: String | D100: Identificador unico del predio a cargo del observatorio | E100: N/A | F100: Obligatorio
B101: CODIGO_OBSERVATORIO | C101: String | D101: Codigo del Observatorio directamente proporcionado una vez que el usuario se haya registrado en la pagina oficial del observatorio Inmobiliario Nacional | E101: N/A | F101: Obligatorio
B102: NUMERO_PREDIAL_ANTIGUO | C102: String | D102: Numero predial actual | E102: N/A | F102: Opcional | G102: Unidad Administrativa Basica | H102: Clase. LC_Predio
B103: NUMERO PREDIAL NUEVO | C103: String | D103: Numero predial Anterior | E103: N/A | F103: Opcional | G103: Unidad Administrativa Basica | H103: Clase. LC_Predio
B104: MATRICULA_INMOBILIARIA | C104: String | D104: Numero de Matricula inmobiliaria | E104: N/A | F104: Opcional | G104: Unidad Administrativa Basica | H104: Clase. LC_Predio
B105: DERECHO_TIPO | C105: Dominio | D105: Derecho que se ejerce sobre el predio | E105: =+DOMINIOS!$C$48 -> Dom_Derecho_Tipo | F105: Opcional | G105: Derechos Responsabilidades, Restricciones (DRR) | H105: Clase. LC_Derecho
B106: RESTRICCION_TIPO | C106: Domino | D106: Restricción legalmente constituida y registrada que afecta el derecho de un persona en relación con el predio | E106: =+DOMINIOS!$C$55 -> Dom_Restricciones_Tipo | F106: Opcional | G106: Derechos Responsabilidades, Restricciones (DRR) | H106: Clase. LC_Derecho
B109: Descripción Tema | C109: Ofertas
C110: Comprende la informacion sobre las ofertas del mercado inmobiliario en predios que se encuetren dentro de las zonas de estudio del gestor catastral
...

Sheet DOMINIOS
B2: Dominio: | C2: Dom_ClaseSueloTipo
B3: CÓDIGO | C3: NOMBRE | D3: DESCRIPCIÓN
B4: 0 | C4: Urbano | D4: Constituyen el suelo urbano, las áreas del territorio distrital o municipal destinadas a usos urbanos por el plan de ordenamiento, que cuenten con infraestructura vial y redes primarias de energía, acueducto y alcantarillado, posibilitándose su urbanización y edificación,
B5: 1 | C5: Rural | D5: Constituyen esta categoría los terrenos no aptos para el uso urbano, por razones de oportunidad, o por su destinación a usos agrícolas, ganaderos, forestales, de explotación de recursos naturales y
B6: 2 | C6: Expansion_Urbana | D6: Constituido por la porción del territorio municipal destinada a la expansión urbana, que se habilitará para el uso urbano durante la vigencia del plan de ordenamiento, según lo determinen los Programas de Ejecución.
B9: Dominio: | C9: Dom_CategoriaSueloTipo
B10: CÓDIGO | C10: NOMBRE | D10: DESCRIPCIÓN
B11: 0 | C11: Suburbano | D11: Constituyen esta categoría las áreas ubicadas dentro del suelo rural, en las que se mezclan los usos del suelo y las formas de vida del campo y la ciudad, diferentes a las clasificadas como áreas de expansión urbana, que pueden ser objeto de desarrollo con restricciones de uso, de intensidad y de densidad, garantizando el autoabastecimiento en servicios públicos domiciliarios,
B12: 1 | C12: Proteccion | D12: Constituido por las zonas y áreas de terrenos localizados dentro de cualquiera de las anteriores clases, que por sus características geográficas, paisajísticas o ambientales, o por formar parte de las zonas de utilidad pública para la ubicación de infraestructuras para la provisión de servicios públicos domiciliarios o de las áreas de amenazas y riesgo no mitigable para la localización de asentamientos humanos, tiene restringida la posibilidad de urbanizarse. (Articulo 35, Ley 388 de 1997)
B15: Dominio: | C15: Dom_AccesoTipo
B16: CÓDIGO | C16: NOMBRE | D16: DESCRIPCIÓN
B17: 0 | C17: Ascensor_a_Piso | D17: Existe acceso mediante un ascensor que da acceso directo al piso.
B18: 1 | C18: Ascensor_Entre_Pisos | D18: Existe acceso mediante un ascensor que da acceso al entrepiso. REVISAR DOCUMENTACIÓN
B19: 2 | C19: Ascensor_Privado | D19: Existe acceso mediante un ascensor que da acceso directo a un espacio privado.
B20: 3 | C20: Escaleras | D20: Existe acceso mediante escaleras.
B21: 4 | C21: Escaleras_Electricas | D21: Existe acceso mediante escaleras eléctricas.
B24: Dominio: | C24: Dom_Predio_Tipo
B25: CÓDIGO | C25: NOMBRE | D25: DESCRIPCIÓN
B26: 0 | C26: Baldio | D26: Es un bien inmueble de propiedad de la Nación y ubicado en zonas rurales.
B27: 1 | C27: Fiscal | D27: Los bienes de la Unión cuyo uso no pertenece generalmente a los habitantes, se llaman bienes de la Unión o bienes fiscales.
B28: 2 | C28: Patrimonial | D28: Son bienes patrimoniales los de titularidad de las administraciones públicas que no tengan el carácter de bienes de dominio público, es decir, que no estén destinados directamente al uso público o afectados a un servicio público. Si no consta la afectación de un bien se presume su carácter patrimonial.
B29: 3 | C29: Uso_Publico | D29: Son aquellos inmuebles de dominio público cuyo uso pertenece a todos los habitantes del territorio nacional, LC_PredioTipo destinados al uso o disfrute colectivo.
B30: 4 | C30: Privado | D30: Es aquel que ha salido del patrimonio del estado, cuenta con un propietario inscrito en el folio de matrícula y se considera propiedad privada en los términos del artículo 48 de la Ley 160 de 1993.
B31: 5 | C31: Territorio_Colectivo | D31: Son los predios adjudicados a comunidades pertenecientes a grupos étnicos en el marco del reconocimiento de los resguardos legalmente constituidos según el Decreto 2164 de 1995 o de las propiedades colectivas de comunidades negras conforme Ley 70 de 1993.
B32: 6 | C32: Vacante | D32: Son bienes inmuebles que se encuentran dentro de territorio respectivo a cargo de la Nación, sin dueño aparente o conocido.
B35: Dominio: | C35: Dom_Condicion_Predio_Tipo
B36: CÓDIGO | C36: NOMBRE | D36: DESCRIPCIÓN
B37: 0 | C37: NPH | D37: Predio no sometido al régimen de propiedad horizontal.
B38: 1 | C38: PH_Matriz | D38: Predio matriz del régimen de propiedad horizontal sobre el cual se segregan todas las unidades prediales.
B39: 2 | C39: PH_Unidad_Predial | D39: Apartamento, garaje, depósito o cualquier otro tipo de unidad predial dentro del PH que se encuentra debidamente inscrito en el registro de instrumentos públicos
B40: 3 | C40: Condominio_Matriz | D40: Predio matriz del condominio sobre el cual se segregan todas las unidades prediales.
B41: 4 | C41: Condominio_Unidad_Predial | D41: Unidad predial dentro del condominio matriz
B42: 5 | C42: Mejora_PH | D42: Mejora sobre un predio sometido a régimen de propiedad horizontal
B43: 6 | C43: Mejora_NPH | D43: Mejora sobre un predio no sometido a régimen de propiedad horizontal.
B44: 7 | C44: Bien_Uso_Publico | D44: Inmuebles que siendo de dominio de la Nación, o una entidad territorial o de particulares, están destinados al uso de los habitantes.
B48: Dominio: | C48: Dom_Derecho_Tipo
B49: CÓDIGO | C49: NOMBRE | D49: DESCRIPCIÓN
B50: 0 | C50: Ocupacion | D50: En el ámbito de la gestión catastral, es el polígono que representa el asentamiento de personas naturales o jurídicas dentro de un terreno baldío, el cual puede contar o no con construcciones y/o edificaciones.
B51: 1 | C51: Posesión | D51: En el ámbito de la gestión catastral, es el polígono que representa el asentamiento de personas naturales o jurídicas, con ánimo de señor y dueño sobre un predio privado, el cual puede contar o no con construcciones y/o edificaciones
B52: 2 | C52: Derecho de Dominio o propiedad | D52: El dominio que se llama también propiedad es el derecho real en una cosa corporal, para gozar y disponer de ella arbitrariamente, no siendo contra ley o contra derecho ajeno.
B55: Dominio: | C55: Dom_Restricciones_Tipo
B56: CÓDIGO | C56: NOMBRE | D56: DESCRIPCIÓN
B57: 0 | C57: Ninguna
B58: 1 | C58: Ambientales
B59: 2 | C59: Desplazamiento_Forzado_Restitucion
B60: 3 | C60: Embargo
B61: 4 | C61: Propiedad_Horizontal_y_Urbanismo
B62: 5 | C62: Prohibiciones_Expresas
B63: 6 | C63: Proteccion_Familia
B64: 7 | C64: Servidumbre
B65: 8 | C65: No_Registrada
B66: 9 | C66: Afectaciones_Interes_General
B69: Dominio: | C69: Dom_Tipo_Oferta
B70: CÓDIGO | C70: NOMBRE | D70: DESCRIPCIÓN
B71: 0 | C71: Venta | D71: Oferta de inmueble en venta
B72: 1 | C72: Arrendamiento | D72: Oferta de inmueble en Arrendamiento
B75: Dominio: | C75: Dom_Destinacion_Economica
B76: CÓDIGO | C76: NOMBRE | D76: DESCRIPCIÓN
B77: 0 | C77: Agricola | D77: Se califica con destino agrícola, aquellos predios con funcionalidad de laboreo agrícola, terrenos que han sido transformados y ocupados para la producción de cultivos cuyo objetivo es satisfacer las necesidades alimentarias, comerciales y agrícolas. En caso de encontrar actividad agrícola y actividad pecuaria en un mismo predio, se califica según la actividad que predomine. Si, ambas actividades tienen el mismo porcentaje de participación en el predio, se debe calificar como agrícola.
B78: 1 | C78: Agroindustrial | D78: Se califica con destino agroindustrial, aquellos predios destinados a la actividad que implica cultivo (producción) y transformación (industrialización y comercialización) de productos agrícola, pecuario y forestal.
B79: 2 | C79: Agroforestal | D79: Se califica con destino agroforestal, aquellos predios destinados al establecimiento y aprovechamiento combinado de especies forestales con actividades agrícolas o pecuarias con arreglos diferenciados. Incluye la actividad agrosilvícola, silvopastoril y agrosilvopastoril.
B80: 3 | C80: Comercial | D80: Se califica con destino comercial, aquellos predios cuya finalidad es la de realizar la actividad económica de ofrecer, transar o almacenar bienes y/o servicios a través de un mercader o comerciante.
B81: 4 | C81: Cultural | D81: Se califica con destino cultural, aquellos predios considerados como bienes culturales de la nación, además los espacios destinados al desarrollo de actividades artísticas.
B82: 5 | C82: Educativo | D82: Se califica con destino educativo, aquellos predios donde se desarrollan actividades académicas, tanto de la educación inicial, preescolar, básica, media y superior. Incluye los jardines, escuelas, colegios, institutos técnicos, fundaciones educativas, centros de investigación y universidades.
B83: 6 | C83: Forestal | D83: Se califica con destino forestal, aquellos predios con áreas naturales o seminaturales, constituidas principalmente por elementos arbóreos de especies nativas, exóticas e introducidas. Incluye las plantaciones forestales comerciales y los bosques naturales y seminaturales.
B84: 7 | C84: Habitacional | D84: Se califica con destino habitacional, aquellos predios de uso residencial cuya finalidad es la vivienda habitual de las personas. Incluye los parqueaderos, garajes y depósitos dentro de propiedad horizontal como también los predios rurales de vivienda campestre
B85: 8 | C85: Industrial | D85: Se califica con destino industrial, aquellos predios donde se desarrollan actividades de producción, fabricación, preparación, recuperación, reproducción, ensamblaje, construcción, transformación, tratamiento y manipulación de materias primas para producir bienes o productos materiales y que no estén clasificados dentro de los predios mineros.
B86: 9 | C86: Institucional | D86: Se califica con destino institucional, aquellos predios destinados a la administración y prestación de servicios del Estado tanto de orden nacional como territorial.
B87: 10 | C87: Lote_Urbanizable_No_Urbanizado | D87: Se califica con este destino, aquellos predios urbanos no construidos, ubicados en terrenos de grandes áreas que no han sido desarrollados y sin restricción legal para adelantar algún tipo de desarrollo urbanístico.
B88: 11 | C88: Lote_Urbanizado_No_Construido | D88: Se califica con este destino, aquellos predios urbanos no construidos, ubicados en zonas urbanizadas, es decir, con infraestructura de servicios públicos e infraestructura vial.
B89: 12 | C89: Lote_No_Urbanizable | D89: Se califica con este destino, aquellos predios urbanos o rurales clasificados por el instrumento de planeación como suelo de protección, también se incluyen los predios con afectación, por ejemplo los utilizados como servidumbres para los servicios públicos.
B92: Dominio: | C92: Dom_ConstruccionesTipo
B93: CÓDIGO | C93: NOMBRE | D93: DESCRIPCIÓN
B94: 0 | C94: Convencional | D94: Se refiere aquellas construcciones de uso residencial, comercial e industrial.
B95: 1 | C95: No_Convencional | D95: Se refiere aquellas construcciones consideradas anexos de construcción.
B98: Dominio: | C98: Dom_UnidadConstruccionTipo
B99: CÓDIGO | C99: NOMBRE | D99: DESCRIPCIÓN
B100: 0 | C100: Residencial | D100: Se refiere aquellas construcciones de uso residencial, comercial e industrial.
B101: 1 | C101: Comercial | D101: Se refiere aquellas construcciones consideradas anexos de construcción.
B102: 2 | C102: Industrial | D102: Tipo de unidad de construcción en uso para vivienda
B103: 3 | C103: Institucional | D103: Tipo de unidad de construcción en uso de actividades comerciales.
C104: Anexo | D104: Tipo de unidad de construcción anexa, por ejemplo, piscinas, cobertizos, canchas de tenis, toboganes.
B107: Dominio: | C107: Ext_Direccion
B108: CÓDIGO | C108: NOMBRE | D108: DESCRIPCIÓN
C109: Codigo_Postal | D109: Código postal.
C110: Clase_Via_Principal | D110: Valores: Avenida_Calle, Avenida_Carrera, Avenida, Autopista, Circunvalar, Calle, Carrera, Diagonal, Transversal, Circular.
C111: Valor_Via_Principal | D111: Numero que acompaña a la clase de vía principal.
C112: Letra_Via_Principal | D112: Letra que acompaña al valor de la vía principal.
C113: Sector_Ciudad | D113: Valores: Norte, Sur, Este, Oeste.
C114: Valor_Via_Generadora | D114: Numero de la vía generadora.
C115: Letra_Via_Generadora | D115: Letra que acompaña al valor de la vía generadora.
C116: Numero_Predio | D116: Distancia entre la vía generadora al acceso del predio.
C117: Sector_Predio | D117: Sector de donde se localiza el predio, ejemplo: Norte, Sur, Este, Oeste.
C118: Complemento | D118: Complemento de la dirección.
C119: Nombre_Predio | D119: Nombre del predio, ejemplo, nombre de los predios en el sector rural. Este valor se diligencia cuando el tipo de dirección es "No_Estructurada".
B122: Dominio: | C122: Dom_ConstruccionPlantaTipo
B123: CÓDIGO | C123: NOMBRE | D123: DESCRIPCIÓN
B124: 0 | C124: Piso | D124: Superficie horizontal de un espacio arquitectónico que divide los espacios en altura.
B125: 1 | C125: Mezanine | D125: Piso intermedio entre los pisos principales de una casa o edificio.
B126: 2 | C126: Sótano | D126: Piso de un edificio situado por debajo del nivel de la calle.
...

Sheet ESPECIFICACIONES
B1: INSTRUCCIONES PARA DILIGENCIAR LOS FORMATOS DE ENTREGA DE DATOS AL OBSERVATORIO INMOBILIARIO NACIONAL
B2: OBSERVACIONES GENERALES
B3: El formato de entrega de datos al observatorio nacional debe ser diligenciado teniendo en cuenta el siguiente diccionario de datos en el cual se especifican cada una de las tablas o capas geograficas que deben ser entregadas por parte de los usuarios.
B4: Los Usuarios tienen dos opciones al momento de reportar la información al Observatorio Nacional y pueden escoger libremente cualquiera de las dos: OPCION 1: El usuario debe proporcionar la información en 5 tablas y una capa geográfica teniendo en cuenta la siguiente diferenciación: CAPA GEOGRAFICAS EN FORMATO GEOPACKAGE: Para esta estructura el usuario debe descargar la base de datos espacial en formato Geopackage proporcionada por el Observatorio inmobiliario Nacional en su sitio web y entregar las siguientes capas geográficas: • Capa Predios: En esta capa se almacena la estructura geográfica y la información espacial asociada a los predios. TABLAS DENTRO DEL GEOPACKAGE • Construcciones: En esta tabla se almacena la información alfanumérica asociada a las construcciones • Terrenos: En esta tabla se almacena la información alfanumérica asociada a los Terrenos. • Tradición: En esta tabla se almacena la información alfanumérica asociada a la tradición de los Predios. • Ofertas: En esta tabla se almacena la información alfanumérica asociada a las ofertas de venta o arrendamiento del sector estudiado por el observatorio. • Avalúos: En esta tabla se almacena la información alfanumérica asociada a los avalúos de los predios. OPCIÓN 2: Para esta opción el usuario debe suministrar la información de las 6 entidades en formato Excel(xlsm), teniendo en cuenta la estructura del diccionario de datos y el ejemplo de presentación de tablas para el observatorio nacional que puede ser descargado en la página web del observatorio TABLAS • Predios En esta tabla se almacena la información alfanumérica asociada a los predios. • Construcciones: En esta tabla se almacena la información alfanumérica asociada a las construcciones • Terrenos: En esta tabla se almacena la información alfanumérica asociada a los Terrenos. • Tradición: En esta tabla se almacena la información alfanumérica asociada a la tradición de los Predios. • Ofertas: En esta tabla se almacena la información alfanumérica asociada a las ofertas de venta o arrendamiento del sector estudiado por el observatorio. • Avalúos: En esta tabla se almacena la información alfanumérica asociada a los avalúos de los predios.
B5: En el diccionario de datos se debe tener en cuenta que algunos campos son obligatorios, otros son condicionales otros opcionales para saber en que momento diligenciar dicho campo favor seguir las siguientes especificaciones.
B6: Obligatorio | C6: El campo tiene que estar diligenciado obligatoriamente.
B7: Condicional | C7: El campo se debe diligenciar o no teniendo en cuenta si la información aplica para los siguientes casos: * Según la coherencia conceptual o lógica: - Cuando el diligenciamiento del campo depende de lo que se haya diligenciado en otro campo. - Por las relaciones entre una capa geográfica con otra capa geográfica o entre una capa geográfica y una tabla. Ejemplos: Campos especificos para los predios bajo el regimen de propiedad Horizontal PH
B8: Opcional | C8: El campo puede estar diligenciado o no.
